{
  "entrypoint": "app.html",
  "shell": "src/main-app.html",
  "fragments": [
    "src/account/sign-in-view.html",
    "src/account/register-view.html",
    "src/account/register-image-view.html",
    "src/account/request-recovery-view.html",
    "src/account/recover-account-view.html",
    "src/account/account-view.html",
    "src/account/edit-profile-view.html",
    "src/about/about-view.html",
    "src/about/learn-card-development-view.html",
    "src/balance/balance-view.html",
    "src/balance/withdraw-dialog.html",
    "src/feed/feed-view.html",
    "src/feed/channel-view.html",
    "src/compose/compose-view.html",
    "src/card/card-page.html",
    "src/dialogs/confirm-dialog.html",
    "src/dialogs/error-dialog.html",
    "src/account/agree-terms-view.html",
    "src/card/card-analytics-dialog.html",
    "src/card/edit/edit-card-dialog.html",
    "src/card/edit/edit-card-content-dialog.html",
    "src/dialogs/share-link-dialog.html",
    "src/dialogs/insufficient-funds-dialog.html",
    "src/compose/compose-card-preview.html",
    "src/card/card-view.html",
    "src/compose/edit-card-summary-dialog.html",
    "src/core/utils/load-image.html"
  ],
  "builds": [
    {
      "name": "es6",
      "bundle": true,
      "sourcemaps": "true",
      "js": {
        "minify": true
      },
      "css": {
        "minify": true
      },
      "html": {
        "minify": true
      }
    },
    {
      "name": "es5",
      "bundle": true,
      "sourcemaps": "true",
      "js": {
        "minify": true,
        "compile": true
      },
      "css": {
        "minify": true
      },
      "html": {
        "minify": true
      }
    }
  ],
  "lint": {
    "rules": [
      "polymer-2"
    ]
  }
}